{
  "general": {
    "level": 2,
    "experience": 0,
    "name": "Elas Dorr",
    "playerName": "Matt",
    "ancestry": "Human",
    "background": "Street Urchin",
    "class": "Monk",
    "alignment": "N",
    "deity": "-",
    "age": 30,
    "gender": "M",
    "languages": [
      "Common",
      "Dwarvish",
      "Gnomish"
    ],
    "speed": 25,
    "heroPoints": 2
  },
  "abilities": [
    {
      "name": "Strength",
      "score": 14
    },
    {
      "name": "Dexterity",
      "score": 18
    },
    {
      "name": "Constitution",
      "score": 14
    },
    {
      "name": "Intelligence",
      "score": 12
    },
    {
      "name": "Wisdom",
      "score": 10
    },
    {
      "name": "Charisma",
      "score": 10
    }
  ],
  "skills": [
    {
      "name": "Acrobatics",
      "ability": "Dexterity",
      "proficiency": "T",
      "fromItems": 0
    },
    {
      "name": "Arcana",
      "ability": "Intelligence",
      "proficiency": "",
      "fromItems": 0
    },
    {
      "name": "Athletics",
      "ability": "Strength",
      "proficiency": "T",
      "fromItems": 0
    },
    {
      "name": "Crafting",
      "ability": "Intelligence",
      "proficiency": "",
      "fromItems": 0
    },
    {
      "name": "Deception",
      "ability": "Charisma",
      "proficiency": "",
      "fromItems": 0
    },
    {
      "name": "Diplomacy",
      "ability": "Charisma",
      "proficiency": "",
      "fromItems": 0
    },
    {
      "name": "Intimidation",
      "ability": "Charisma",
      "proficiency": "T",
      "fromItems": 0
    },
    {
      "name": "Lore",
      "ability": "Intelligence",
      "proficiency": "T",
      "fromItems": 0
    },
    {
      "name": "Medicine",
      "ability": "Wisdom",
      "proficiency": "",
      "fromItems": 0
    },
    {
      "name": "Nature",
      "ability": "Wisdom",
      "proficiency": "",
      "fromItems": 0
    },
    {
      "name": "Occultism",
      "ability": "Intelligence",
      "proficiency": "",
      "fromItems": 0
    },
    {
      "name": "Perception",
      "ability": "Wisdom",
      "proficiency": "T",
      "fromItems": 0
    },
    {
      "name": "Performance",
      "ability": "Charisma",
      "proficiency": "",
      "fromItems": 0
    },
    {
      "name": "Religion",
      "ability": "Wisdom",
      "proficiency": "",
      "fromItems": 0
    },
    {
      "name": "Society",
      "ability": "Intelligence",
      "proficiency": "",
      "fromItems": 0
    },
    {
      "name": "Stealth",
      "ability": "Dexterity",
      "proficiency": "T",
      "fromItems": 0
    },
    {
      "name": "Survival",
      "ability": "Wisdom",
      "proficiency": "T",
      "fromItems": 0
    },
    {
      "name": "Thievery",
      "ability": "Dexterity",
      "proficiency": "T",
      "fromItems": 0
    }
  ],
  "offense": {
    "attacks": [
      {
        "name": "Unarmed",
        "toHit": {
          "proficiency": "T",
          "ability": "Dexterity",
          "fromItems": 0
        },
        "damage": {
          "die": "1d6",
          "ability": "Strength",
          "damageType": "BPS",
          "other": 0,
          "traits": "Agile/Finesse/Nonlethal/Unarmed"
        }
      },
      {
        "name": "Crane Wing",
        "toHit": {
          "proficiency": "T",
          "ability": "Dexterity",
          "fromItems": 0
        },
        "damage": {
          "die": "1d6",
          "ability": "Strength",
          "damageType": "B",
          "other": 0,
          "traits": "Agile/Finesse/Nonlethal/Unarmed"
        }
      },
      {
        "name": "Wolf Jaw",
        "toHit": {
          "proficiency": "T",
          "ability": "Dexterity",
          "fromItems": 0
        },
        "damage": {
          "die": "1d8",
          "ability": "Strength",
          "damageType": "P",
          "other": 0,
          "traits": "Agile/Finesse/Nonlethal/Unarmed/Backstabber(/Trip)"
        }
      },
      {
        "name": "Dart",
        "toHit": {
          "proficiency": "T",
          "ability": "Dexterity",
          "fromItems": 0
        },
        "damage": {
          "die": "1d4",
          "ability": "",
          "damageType": "P",
          "other": 2,
          "traits": ""
        }
      },
      {
        "name": "Bo staff",
        "toHit": {
          "proficiency": "",
          "ability": "Strength",
          "fromItems": 0
        },
        "damage": {
          "die": "1d6",
          "ability": "Strength",
          "damageType": "B",
          "other": 0,
          "traits": "Monk/Parry/Reach/Trip"
        }
      }
    ]
  },
  "defense": {
    "health": {
      "max": 34,
      "current": 34,
      "temporary": 0
    },
    "armorClass": {
      "wearing": "Clothing (Explorer's)",
      "dexterityCap": 5,
      "proficiency": "E",
      "fromItems": 0
    },
    "savingThrows": [
      {
        "name": "Fortitude",
        "ability": "Constitution",
        "proficiency": "E",
        "fromItems": 0
      },
      {
        "name": "Reflex",
        "ability": "Dexterity",
        "proficiency": "E",
        "fromItems": 0
      },
      {
        "name": "Will",
        "ability": "Wisdom",
        "proficiency": "E",
        "fromItems": 0
      }
    ]
  },
  "feats": {
    "ancestry": [
      "Versatile Heritage"
    ],
    "class": [
      "Crane Stance",
      "Wolf Stance"
    ],
    "skill": [
      "Pickpocket",
      "Titan Wrestler"
    ],
    "general": [
      "Toughness"
    ]
  },
  "gear": {
    "items": [
      "Adventurer's Pack",
      "Climbing Kit",
      "Clothing (Explorer's)",
      "Clothing (Winter)",
      "Thieves' Tools"
    ],
    "money": {
      "pp": 0,
      "gp": 10,
      "sp": 0,
      "cp": 6
    }
  },
  "classFeatures": [
    "Powerful Fist",
    "Flurry of Blows",
    "Stunning Fist"
  ]
}
